tcversioner.py
vcversioner.py
tcversioner-2.16.0.0.post6.dist-info/DESCRIPTION.rst
tcversioner-2.16.0.0.post6.dist-info/METADATA
tcversioner-2.16.0.0.post6.dist-info/RECORD
tcversioner-2.16.0.0.post6.dist-info/WHEEL
tcversioner-2.16.0.0.post6.dist-info/entry_points.txt
tcversioner-2.16.0.0.post6.dist-info/metadata.json
tcversioner-2.16.0.0.post6.dist-info/top_level.txt
