Metadata-Version: 2.0
Name: tcversioner
Version: 2.16.0.0.post6
Summary: Use version control tags to discover version numbers
Home-page: https://github.com/tylercrumpton/vcversioner
Author: Tyler Crumpton
Author-email: tyler.crumpton@gmail.com
License: ISC
Platform: UNKNOWN
Classifier: Development Status :: 3 - Alpha
Classifier: Intended Audience :: Developers
Classifier: License :: OSI Approved :: ISC License (ISCL)
Classifier: Operating System :: OS Independent
Classifier: Programming Language :: Python :: 2
Classifier: Programming Language :: Python :: 2.6
Classifier: Programming Language :: Python :: 2.7
Classifier: Programming Language :: Python :: 3
Classifier: Programming Language :: Python :: 3.3
Classifier: Programming Language :: Python :: 3.4
Classifier: Programming Language :: Python :: 3.5
Classifier: Topic :: Software Development :: Version Control
